actuator/bindings.cpython-311-aarch64-linux-gnu.so
actuator/__init__.py
actuator/requirements-dev.txt
actuator/bindings.pyi
actuator/requirements.txt
actuator/py.typed
actuator/robstride/Cargo.toml
actuator/robstride/README.md
actuator/robstride/src/main.rs
actuator/robstride/src/supervisor.rs
actuator/robstride/src/transport.rs
actuator/robstride/src/actuator_types.rs
actuator/robstride/src/actuator.rs
actuator/robstride/src/lib.rs
actuator/robstride/src/protocol.rs
actuator/robstride/src/bin/test_serdes.rs
actuator/robstride/src/bin/test_motor.rs
actuator/robstride/src/actuators/mod.rs
actuator/robstride/src/actuators/robstride04.rs
actuator/robstride/src/actuators/robstride03.rs
actuator/robstride/src/actuators/robstride01.rs
actuator/robstride/src/actuators/robstride00.rs
actuator/robstride/src/actuators/robstride02.rs
actuator/bindings/pyproject.toml
actuator/bindings/Cargo.toml
actuator/bindings/src/lib.rs
actuator/bindings/src/bin/stub_gen.rs
actuator-0.3.4.dist-info/LICENSE
actuator-0.3.4.dist-info/WHEEL
actuator-0.3.4.dist-info/METADATA
actuator-0.3.4.dist-info/top_level.txt
actuator-0.3.4.dist-info/RECORD
