Metadata-Version: 2.2
Name: actuator
Version: 0.3.4
Summary: Python interface for controlling various robotic actuators
Home-page: https://github.com/kscalelabs/actuator
Author: K-Scale Labs
Requires-Python: >=3.11
License-File: LICENSE
Provides-Extra: dev
Requires-Dist: black; extra == "dev"
Requires-Dist: darglint; extra == "dev"
Requires-Dist: mypy; extra == "dev"
Requires-Dist: pytest; extra == "dev"
Requires-Dist: ruff; extra == "dev"
Requires-Dist: python-can; extra == "dev"
Requires-Dist: pyserial; extra == "dev"
Dynamic: author
Dynamic: description
Dynamic: description-content-type
Dynamic: home-page
Dynamic: provides-extra
Dynamic: requires-python
Dynamic: summary
